odoo/addons/mrp_product_characterisation/README.rst
odoo/addons/mrp_product_characterisation/__init__.py
odoo/addons/mrp_product_characterisation/__manifest__.py
odoo/addons/mrp_product_characterisation/i18n/fr.po
odoo/addons/mrp_product_characterisation/i18n/it.po
odoo/addons/mrp_product_characterisation/i18n/mrp_product_characterisation.pot
odoo/addons/mrp_product_characterisation/models/__init__.py
odoo/addons/mrp_product_characterisation/models/product_product.py
odoo/addons/mrp_product_characterisation/models/product_template.py
odoo/addons/mrp_product_characterisation/readme/CONTRIBUTORS.rst
odoo/addons/mrp_product_characterisation/readme/DESCRIPTION.rst
odoo/addons/mrp_product_characterisation/static/description/icon.png
odoo/addons/mrp_product_characterisation/static/description/index.html
odoo/addons/mrp_product_characterisation/static/description/intermediate_product.png
odoo/addons/mrp_product_characterisation/tests/__init__.py
odoo/addons/mrp_product_characterisation/tests/test_product.py
odoo/addons/mrp_product_characterisation/views/view_mrp_bom.xml
odoo/addons/mrp_product_characterisation/views/view_product_product.xml
odoo/addons/mrp_product_characterisation/views/view_product_template.xml
odoo_addon_mrp_product_characterisation-16.0.1.1.0.dist-info/METADATA
odoo_addon_mrp_product_characterisation-16.0.1.1.0.dist-info/WHEEL
odoo_addon_mrp_product_characterisation-16.0.1.1.0.dist-info/top_level.txt
odoo_addon_mrp_product_characterisation-16.0.1.1.0.dist-info/RECORD
